arelle/Cntlr.py
arelle/CntlrCmdLine.py
arelle/CntlrComServer.py
arelle/CntlrProfiler.py
arelle/CntlrQuickBooks.py
arelle/CntlrWebMain.py
arelle/CntlrWinMain.py
arelle/CntlrWinTooltip.py
arelle/DialogAbout.py
arelle/DialogArcroleGroup.py
arelle/DialogFind.py
arelle/DialogFormulaParameters.py
arelle/DialogLanguage.py
arelle/DialogNewFactItem.py
arelle/DialogOpenArchive.py
arelle/DialogOpenTaxonomyPackage.py
arelle/DialogPackageManager.py
arelle/DialogPluginManager.py
arelle/DialogRssWatch.py
arelle/DialogURL.py
arelle/DialogUserPassword.py
arelle/DisclosureSystem.py
arelle/FileSource.py
arelle/FormulaConsisAsser.py
arelle/FormulaEvaluator.py
arelle/FunctionCustom.py
arelle/FunctionFn.py
arelle/FunctionIxt.py
arelle/FunctionUtil.py
arelle/FunctionXfi.py
arelle/FunctionXs.py
arelle/HashUtil.py
arelle/HtmlUtil.py
arelle/InstanceAspectsEvaluator.py
arelle/LeiUtil.py
arelle/LocalViewer.py
arelle/Locale.py
arelle/ModelDocument.py
arelle/ModelDtsObject.py
arelle/ModelFormulaObject.py
arelle/ModelInstanceObject.py
arelle/ModelManager.py
arelle/ModelObject.py
arelle/ModelObjectFactory.py
arelle/ModelRelationshipSet.py
arelle/ModelRenderingObject.py
arelle/ModelRssItem.py
arelle/ModelRssObject.py
arelle/ModelTestcaseObject.py
arelle/ModelValue.py
arelle/ModelVersObject.py
arelle/ModelVersReport.py
arelle/ModelXbrl.py
arelle/PackageManager.py
arelle/PluginManager.py
arelle/PrototypeDtsObject.py
arelle/PrototypeInstanceObject.py
arelle/PythonUtil.py
arelle/RenderingEvaluator.py
arelle/RenderingResolver.py
arelle/TableStructure.py
arelle/TkTableWrapper.py
arelle/UITkTable.py
arelle/UiUtil.py
arelle/Updater.py
arelle/UrlUtil.py
arelle/Validate.py
arelle/ValidateFilingText.py
arelle/ValidateFormula.py
arelle/ValidateInfoset.py
arelle/ValidateUtr.py
arelle/ValidateVersReport.py
arelle/ValidateXbrl.py
arelle/ValidateXbrlCalcs.py
arelle/ValidateXbrlDTS.py
arelle/ValidateXbrlDimensions.py
arelle/Version.py
arelle/ViewFile.py
arelle/ViewFileConcepts.py
arelle/ViewFileDTS.py
bis_arelle-2022.6.14.151921.dist-info/LICENSE
bis_arelle-2022.6.14.151921.dist-info/METADATA
bis_arelle-2022.6.14.151921.dist-info/WHEEL
bis_arelle-2022.6.14.151921.dist-info/top_level.txt
bis_arelle-2022.6.14.151921.dist-info/RECORD
