Metadata-Version: 2.1
Name: bis-arelle
Version: 2022.6.14.151921
Summary: BIS flavor of arelle which includes only subdir "arelle" of the original project
Home-page: https://www.bis.ru
Author: Banking Information Systems
Author-email: sklimov@bis.ru
Classifier: Development Status :: 3 - Alpha
Classifier: Intended Audience :: Developers
Classifier: License :: OSI Approved :: Apache Software License
Classifier: Natural Language :: English
Classifier: Programming Language :: Python :: 3
Classifier: Programming Language :: Python :: 3.8
Classifier: Operating System :: OS Independent
Classifier: Topic :: Office/Business :: Financial :: Spreadsheet
Classifier: Topic :: Text Processing :: Markup :: XML
Requires-Python: >=3.8
License-File: LICENSE
